{
  "$schema": "https://schema.management.azure.com/schemas/2019-04-01/deploymentTemplate.json#",
  "contentVersion": "1.0.0.0",
  "parameters": {
    "ApimServiceName": {
      "type": "string",
      "metadata": {
        "description": "Name of the API Management"
      }
    },
    "LinkedTemplatesBaseUrl": {
      "type": "string",
      "metadata": {
        "description": "Base URL of the repository"
      }
    }
  },
  "resources": [
    {
      "properties": {
        "mode": "Incremental",
        "templateLink": {
          "uri": "[concat(parameters('LinkedTemplatesBaseUrl'), '/SimpleAPIService-apiVersionSets.template.json')]",
          "contentVersion": "1.0.0.0"
        },
        "parameters": {
          "ApimServiceName": {
            "value": "[parameters('ApimServiceName')]"
          }
        }
      },
      "name": "versionSetTemplate",
      "type": "Microsoft.Resources/deployments",
      "apiVersion": "2018-05-01",
      "dependsOn": []
    },
    {
      "properties": {
        "mode": "Incremental",
        "templateLink": {
          "uri": "[concat(parameters('LinkedTemplatesBaseUrl'), '/SimpleAPI-initial.api.template.json')]",
          "contentVersion": "1.0.0.0"
        },
        "parameters": {
          "ApimServiceName": {
            "value": "[parameters('ApimServiceName')]"
          }
        }
      },
      "name": "SimpleAPI-InitialAPITemplate",
      "type": "Microsoft.Resources/deployments",
      "apiVersion": "2018-05-01",
      "dependsOn": []
    },
    {
      "properties": {
        "mode": "Incremental",
        "templateLink": {
          "uri": "[concat(parameters('LinkedTemplatesBaseUrl'), '/SimpleAPI-subsequent.api.template.json')]",
          "contentVersion": "1.0.0.0"
        },
        "parameters": {
          "ApimServiceName": {
            "value": "[parameters('ApimServiceName')]"
          }
        }
      },
      "name": "SimpleAPI-SubsequentAPITemplate",
      "type": "Microsoft.Resources/deployments",
      "apiVersion": "2018-05-01",
      "dependsOn": [
        "[resourceId('Microsoft.Resources/deployments', 'SimpleAPI-InitialAPITemplate')]"
      ]
    }
  ]
}